causally/__init__.py
causally/quick_test.py
causally/datasets/__init__.py
causally/graph/__init__.py
causally/graph/random_graph.py
causally/scm/__init__.py
causally/scm/causal_mechanism.py
causally/scm/context.py
causally/scm/noise.py
causally/scm/scm.py
causally/scm/scm_property.py
causally/utils/__init__.py
causally/utils/graph.py
causally-0.1.0.dist-info/LICENSE
causally-0.1.0.dist-info/METADATA
causally-0.1.0.dist-info/WHEEL
causally-0.1.0.dist-info/top_level.txt
causally-0.1.0.dist-info/RECORD
