Metadata-Version: 2.2
Name: causally
Version: 0.1.0
Summary: Generator of causal discovery data under realistic assumptions.
Author-email: Francesco Montagna <francesco.montagna997@gmail.com>
License: MIT
Project-URL: Homepage, https://github.com/francescomontagna/causally
Project-URL: Repository, https://github.com/francescomontagna/causally
Requires-Python: >=3.8
License-File: LICENSE
Requires-Dist: numpy>=1.25.2
Requires-Dist: networkx>=3.1
Requires-Dist: scikit-learn>=1.3.0
Requires-Dist: torch>=2.0.1
Requires-Dist: python-igraph>=0.11.2
